{
  "scan_date": "2026-07-14",
  "mode": "ORTA",
  "total_scanned": 175,
  "buy_count": 44,
  "sell_count": 0,
  "hold_count": 131,
  "error_count": 10,
  "market_volatility": "Yüksek ⚠️",
  "buy_signals": [
    {
      "symbol": "AKBNK",
      "probability": 0.9990742206573486,
      "signal": "BUY",
      "confidence": 0.9990742206573486,
      "current_price": 67.5999984741211,
      "sentiment_score": 0.0,
      "change_1d": 0.2223892255977566,
      "rsi": 36.579769270859366,
      "volatility": 0.09655780650808948,
      "target_price": 72.33199836730958,
      "horizon_days": 10,
      "history_info": "Önceki AL: 68.75 TL (2026-07-13), Mevcut Getiri: %-1.7",
      "reason": "Strong bullish signal (99.9%) > 70.0%",
      "timestamp": "2026-07-14 06:35:33.195833"
    },
    {
      "symbol": "AKSEN",
      "probability": 0.7026839256286621,
      "signal": "BUY",
      "confidence": 0.7026839256286621,
      "current_price": 91.9000015258789,
      "sentiment_score": 0.0,
      "change_1d": 0.38230307204164926,
      "rsi": 61.78050848638031,
      "volatility": 0.1258271311316045,
      "target_price": 98.33300163269044,
      "horizon_days": 10,
      "history_info": "Önceki AL: 91.50 TL (2026-07-13), Mevcut Getiri: %+0.4",
      "reason": "Strong bullish signal (70.3%) > 70.0%",
      "timestamp": "2026-07-14 06:35:36.534509"
    },
    {
      "symbol": "AYCES",
      "probability": 0.9542821049690247,
      "signal": "BUY",
      "confidence": 0.9542821049690247,
      "current_price": 519.0,
      "sentiment_score": 0.0,
      "change_1d": -0.5747126436781609,
      "rsi": 23.72713108959404,
      "volatility": 0.09328543171792761,
      "target_price": 555.33,
      "horizon_days": 10,
      "history_info": "Önceki AL: 574.50 TL (2026-07-06), Mevcut Getiri: %-9.7",
      "reason": "Strong bullish signal (95.4%) > 70.0%",
      "timestamp": "2026-07-14 06:35:45.111423"
    },
    {
      "symbol": "BANVT",
      "probability": 0.9737474918365479,
      "signal": "BUY",
      "confidence": 0.9737474918365479,
      "current_price": 164.5,
      "sentiment_score": 0.0,
      "change_1d": 0.4273485562884888,
      "rsi": 42.146353037084786,
      "volatility": 0.0904454869652753,
      "target_price": 176.01500000000001,
      "horizon_days": 10,
      "history_info": "Önceki AL: 167.10 TL (2026-07-13), Mevcut Getiri: %-1.6",
      "reason": "Strong bullish signal (97.4%) > 70.0%",
      "timestamp": "2026-07-14 06:35:48.216129"
    },
    {
      "symbol": "BIZIM",
      "probability": 0.9174162149429321,
      "signal": "BUY",
      "confidence": 0.9174162149429321,
      "current_price": 24.959999084472656,
      "sentiment_score": 0.0,
      "change_1d": -0.2398136378626535,
      "rsi": 16.117434301051105,
      "volatility": 0.0473843674446612,
      "target_price": 26.707199020385744,
      "horizon_days": 10,
      "history_info": "Önceki AL: 25.38 TL (2026-07-13), Mevcut Getiri: %-1.7",
      "reason": "Strong bullish signal (91.7%) > 70.0%",
      "timestamp": "2026-07-14 06:35:53.678926"
    },
    {
      "symbol": "BRISA",
      "probability": 0.9992105960845947,
      "signal": "BUY",
      "confidence": 0.9992105960845947,
      "current_price": 80.9000015258789,
      "sentiment_score": 0.0,
      "change_1d": -0.18507281953230353,
      "rsi": 42.09661965300686,
      "volatility": 0.07670929907186265,
      "target_price": 86.56300163269043,
      "horizon_days": 10,
      "history_info": "Önceki AL: 81.90 TL (2026-07-08), Mevcut Getiri: %-1.2",
      "reason": "Strong bullish signal (99.9%) > 70.0%",
      "timestamp": "2026-07-14 06:35:54.606979"
    },
    {
      "symbol": "CEMTS",
      "probability": 0.9992127418518066,
      "signal": "BUY",
      "confidence": 0.9992127418518066,
      "current_price": 9.239999771118164,
      "sentiment_score": 0.0,
      "change_1d": -0.4310340840949625,
      "rsi": 10.123871315154531,
      "volatility": 0.07217088787004527,
      "target_price": 9.886799755096437,
      "horizon_days": 10,
      "history_info": "Önceki AL: 9.54 TL (2026-07-10), Mevcut Getiri: %-3.1",
      "reason": "Strong bullish signal (99.9%) > 70.0%",
      "timestamp": "2026-07-14 06:36:00.667875"
    },
    {
      "symbol": "CLEBI",
      "probability": 0.9182838201522827,
      "signal": "BUY",
      "confidence": 0.9182838201522827,
      "current_price": 1545.0,
      "sentiment_score": 0.0,
      "change_1d": -0.0646830530401035,
      "rsi": 46.34884471659279,
      "volatility": 0.056261199672863464,
      "target_price": 1653.15,
      "horizon_days": 10,
      "history_info": "Önceki AL: 1525.00 TL (2026-07-10), Mevcut Getiri: %+1.3",
      "reason": "Strong bullish signal (91.8%) > 70.0%",
      "timestamp": "2026-07-14 06:36:02.572408"
    },
    {
      "symbol": "ESCOM",
      "probability": 0.9996368885040283,
      "signal": "BUY",
      "confidence": 0.9996368885040283,
      "current_price": 5.710000038146973,
      "sentiment_score": 0.0,
      "change_1d": -0.17482084635430886,
      "rsi": 22.596179899188286,
      "volatility": 0.11025276238895988,
      "target_price": 6.109700040817261,
      "horizon_days": 10,
      "history_info": "Önceki AL: 5.92 TL (2026-07-10), Mevcut Getiri: %-3.5",
      "reason": "Strong bullish signal (100.0%) > 70.0%",
      "timestamp": "2026-07-14 06:36:18.764943"
    },
    {
      "symbol": "GARAN",
      "probability": 0.9986203908920288,
      "signal": "BUY",
      "confidence": 0.9986203908920288,
      "current_price": 126.30000305175781,
      "sentiment_score": 0.0,
      "change_1d": -0.07911271591291891,
      "rsi": 30.0598988585008,
      "volatility": 0.09597560297737837,
      "target_price": 135.14100326538087,
      "horizon_days": 10,
      "history_info": "Önceki AL: 128.50 TL (2026-07-13), Mevcut Getiri: %-1.7",
      "reason": "Strong bullish signal (99.9%) > 70.0%",
      "timestamp": "2026-07-14 06:36:23.167175"
    },
    {
      "symbol": "GESAN",
      "probability": 0.9996803998947144,
      "signal": "BUY",
      "confidence": 0.9996803998947144,
      "current_price": 78.8499984741211,
      "sentiment_score": 0.0,
      "change_1d": -0.9422110733379399,
      "rsi": 32.87705862130916,
      "volatility": 0.09013248691594121,
      "target_price": 84.36949836730957,
      "horizon_days": 10,
      "history_info": "Önceki AL: 80.25 TL (2026-07-13), Mevcut Getiri: %-1.7",
      "reason": "Strong bullish signal (100.0%) > 70.0%",
      "timestamp": "2026-07-14 06:36:25.658292"
    },
    {
      "symbol": "GLYHO",
      "probability": 0.9982607960700989,
      "signal": "BUY",
      "confidence": 0.9982607960700989,
      "current_price": 17.100000381469727,
      "sentiment_score": 0.0,
      "change_1d": -0.2915407473626039,
      "rsi": 33.145725143839186,
      "volatility": 0.09063907357317959,
      "target_price": 18.297000408172607,
      "horizon_days": 10,
      "history_info": "Önceki AL: 17.26 TL (2026-07-13), Mevcut Getiri: %-0.9",
      "reason": "Strong bullish signal (99.8%) > 70.0%",
      "timestamp": "2026-07-14 06:36:27.162392"
    },
    {
      "symbol": "GOLTS",
      "probability": 0.9908915162086487,
      "signal": "BUY",
      "confidence": 0.9908915162086487,
      "current_price": 316.25,
      "sentiment_score": 0.0,
      "change_1d": -0.15785319652722968,
      "rsi": 34.72487460684515,
      "volatility": 0.043351599405008885,
      "target_price": 338.38750000000005,
      "horizon_days": 10,
      "history_info": "Önceki AL: 325.50 TL (2026-07-08), Mevcut Getiri: %-2.8",
      "reason": "Strong bullish signal (99.1%) > 70.0%",
      "timestamp": "2026-07-14 06:36:28.239063"
    },
    {
      "symbol": "HALKB",
      "probability": 0.9996082186698914,
      "signal": "BUY",
      "confidence": 0.9996082186698914,
      "current_price": 39.29999923706055,
      "sentiment_score": 0.0,
      "change_1d": -0.6069845040710363,
      "rsi": 15.330503202194464,
      "volatility": 0.08850008102861585,
      "target_price": 42.05099918365479,
      "horizon_days": 10,
      "history_info": "Önceki AL: 40.52 TL (2026-07-13), Mevcut Getiri: %-3.0",
      "reason": "Strong bullish signal (100.0%) > 70.0%",
      "timestamp": "2026-07-14 06:36:32.593923"
    },
    {
      "symbol": "INDES",
      "probability": 0.9360167980194092,
      "signal": "BUY",
      "confidence": 0.9360167980194092,
      "current_price": 10.5600004196167,
      "sentiment_score": 0.0,
      "change_1d": -0.1890312309411612,
      "rsi": 41.86643475151269,
      "volatility": 0.1370584108811293,
      "target_price": 11.299200448989868,
      "horizon_days": 10,
      "history_info": "Önceki AL: 10.45 TL (2026-07-10), Mevcut Getiri: %+1.1",
      "reason": "Strong bullish signal (93.6%) > 70.0%",
      "timestamp": "2026-07-14 06:36:39.373345"
    },
    {
      "symbol": "ISCTR",
      "probability": 0.9967747330665588,
      "signal": "BUY",
      "confidence": 0.9967747330665588,
      "current_price": 13.699999809265137,
      "sentiment_score": 0.0,
      "change_1d": -0.07294112949679872,
      "rsi": 46.93108341155066,
      "volatility": 0.0895261405502435,
      "target_price": 14.658999795913697,
      "horizon_days": 10,
      "history_info": "Önceki AL: 13.76 TL (2026-07-13), Mevcut Getiri: %-0.4",
      "reason": "Strong bullish signal (99.7%) > 70.0%",
      "timestamp": "2026-07-14 06:36:41.127871"
    },
    {
      "symbol": "ISGYO",
      "probability": 0.8581437468528748,
      "signal": "BUY",
      "confidence": 0.8581437468528748,
      "current_price": 26.719999313354492,
      "sentiment_score": 0.0,
      "change_1d": 1.0589968745885838,
      "rsi": 45.61451543297729,
      "volatility": 0.2815361938853861,
      "target_price": 28.590399265289307,
      "horizon_days": 10,
      "history_info": "Önceki AL: 27.34 TL (2026-07-13), Mevcut Getiri: %-2.3",
      "reason": "Strong bullish signal (85.8%) > 70.0%",
      "timestamp": "2026-07-14 06:36:43.238366"
    },
    {
      "symbol": "JANTS",
      "probability": 0.994941234588623,
      "signal": "BUY",
      "confidence": 0.994941234588623,
      "current_price": 16.100000381469727,
      "sentiment_score": 0.0,
      "change_1d": 0.37406148701837666,
      "rsi": 31.696625195724735,
      "volatility": 0.09260915549921307,
      "target_price": 17.227000408172607,
      "horizon_days": 10,
      "history_info": "Önceki AL: 16.47 TL (2026-07-13), Mevcut Getiri: %-2.2",
      "reason": "Strong bullish signal (99.5%) > 70.0%",
      "timestamp": "2026-07-14 06:36:45.771107"
    },
    {
      "symbol": "KARSN",
      "probability": 0.9989990592002869,
      "signal": "BUY",
      "confidence": 0.9989990592002869,
      "current_price": 10.970000267028809,
      "sentiment_score": 0.0,
      "change_1d": -0.36330573134865135,
      "rsi": 9.002414056304787,
      "volatility": 0.09899720787760516,
      "target_price": 11.737900285720826,
      "horizon_days": 10,
      "history_info": "Önceki AL: 12.80 TL (2026-07-06), Mevcut Getiri: %-14.3",
      "reason": "Strong bullish signal (99.9%) > 70.0%",
      "timestamp": "2026-07-14 06:36:47.610022"
    },
    {
      "symbol": "KAYSE",
      "probability": 0.8681085705757141,
      "signal": "BUY",
      "confidence": 0.8681085705757141,
      "current_price": 4.130000114440918,
      "sentiment_score": 0.0,
      "change_1d": -0.4819272401665552,
      "rsi": 24.533007813660348,
      "volatility": 0.051905446320395614,
      "target_price": 4.419100122451782,
      "horizon_days": 10,
      "history_info": "Önceki AL: 4.37 TL (2026-07-03), Mevcut Getiri: %-5.5",
      "reason": "Strong bullish signal (86.8%) > 70.0%",
      "timestamp": "2026-07-14 06:36:49.509475"
    },
    {
      "symbol": "KLMSN",
      "probability": 0.8204653859138489,
      "signal": "BUY",
      "confidence": 0.8204653859138489,
      "current_price": 29.860000610351562,
      "sentiment_score": 0.0,
      "change_1d": -0.928993977992715,
      "rsi": 13.7568141696743,
      "volatility": 0.08619145077732103,
      "target_price": 31.950200653076173,
      "horizon_days": 10,
      "history_info": "Önceki AL: 33.04 TL (2026-07-08), Mevcut Getiri: %-9.6",
      "reason": "Strong bullish signal (82.0%) > 70.0%",
      "timestamp": "2026-07-14 06:36:53.457987"
    },
    {
      "symbol": "KMPUR",
      "probability": 0.9818331599235535,
      "signal": "BUY",
      "confidence": 0.9818331599235535,
      "current_price": 17.950000762939453,
      "sentiment_score": 0.0,
      "change_1d": -0.5540081902927468,
      "rsi": 45.3182196264499,
      "volatility": 0.0853960461171287,
      "target_price": 19.206500816345216,
      "horizon_days": 10,
      "history_info": "Önceki AL: 18.41 TL (2026-07-03), Mevcut Getiri: %-2.5",
      "reason": "Strong bullish signal (98.2%) > 70.0%",
      "timestamp": "2026-07-14 06:36:54.411185"
    },
    {
      "symbol": "KRTEK",
      "probability": 0.998354434967041,
      "signal": "BUY",
      "confidence": 0.998354434967041,
      "current_price": 22.200000762939453,
      "sentiment_score": 0.0,
      "change_1d": 0.0,
      "rsi": 38.56708319830238,
      "volatility": 0.0637313565859015,
      "target_price": 23.754000816345215,
      "horizon_days": 10,
      "history_info": "Önceki AL: 22.40 TL (2026-07-13), Mevcut Getiri: %-0.9",
      "reason": "Strong bullish signal (99.8%) > 70.0%",
      "timestamp": "2026-07-14 06:36:59.981573"
    },
    {
      "symbol": "KTLEV",
      "probability": 0.9071488976478577,
      "signal": "BUY",
      "confidence": 0.9071488976478577,
      "current_price": 190.3000030517578,
      "sentiment_score": 0.0,
      "change_1d": 2.311829597719254,
      "rsi": 55.00180895739186,
      "volatility": 0.16414400444341193,
      "target_price": 203.62100326538086,
      "horizon_days": 10,
      "history_info": "Önceki AL: 189.10 TL (2026-07-13), Mevcut Getiri: %+0.6",
      "reason": "Strong bullish signal (90.7%) > 70.0%",
      "timestamp": "2026-07-14 06:37:00.874620"
    },
    {
      "symbol": "LOGO",
      "probability": 0.9922674298286438,
      "signal": "BUY",
      "confidence": 0.9922674298286438,
      "current_price": 134.1999969482422,
      "sentiment_score": 0.0,
      "change_1d": 0.0,
      "rsi": 29.20950989600523,
      "volatility": 0.07560560613235064,
      "target_price": 143.59399673461914,
      "horizon_days": 10,
      "history_info": "Önceki AL: 136.50 TL (2026-07-13), Mevcut Getiri: %-1.7",
      "reason": "Strong bullish signal (99.2%) > 70.0%",
      "timestamp": "2026-07-14 06:37:03.829842"
    },
    {
      "symbol": "MOBTL",
      "probability": 0.9920267462730408,
      "signal": "BUY",
      "confidence": 0.9920267462730408,
      "current_price": 14.649999618530273,
      "sentiment_score": 0.0,
      "change_1d": -0.7452615761910171,
      "rsi": 43.52021665407976,
      "volatility": 0.09112759023537287,
      "target_price": 15.675499591827393,
      "horizon_days": 10,
      "history_info": "Önceki AL: 14.75 TL (2026-07-13), Mevcut Getiri: %-0.7",
      "reason": "Strong bullish signal (99.2%) > 70.0%",
      "timestamp": "2026-07-14 06:37:12.135661"
    },
    {
      "symbol": "OBASE",
      "probability": 0.9802636504173279,
      "signal": "BUY",
      "confidence": 0.9802636504173279,
      "current_price": 40.81999969482422,
      "sentiment_score": 0.0,
      "change_1d": -0.43902513457507625,
      "rsi": 47.70801998150837,
      "volatility": 0.21866866555098452,
      "target_price": 43.67739967346191,
      "horizon_days": 10,
      "history_info": "Önceki AL: 41.28 TL (2026-07-13), Mevcut Getiri: %-1.1",
      "reason": "Strong bullish signal (98.0%) > 70.0%",
      "timestamp": "2026-07-14 06:37:16.628055"
    },
    {
      "symbol": "OFSYM",
      "probability": 0.9992621541023254,
      "signal": "BUY",
      "confidence": 0.9992621541023254,
      "current_price": 53.849998474121094,
      "sentiment_score": 0.0,
      "change_1d": -0.0927700377407311,
      "rsi": 30.5191726465375,
      "volatility": 0.08522442676924505,
      "target_price": 57.619498367309575,
      "horizon_days": 10,
      "history_info": "Önceki AL: 55.05 TL (2026-07-10), Mevcut Getiri: %-2.2",
      "reason": "Strong bullish signal (99.9%) > 70.0%",
      "timestamp": "2026-07-14 06:37:18.646957"
    },
    {
      "symbol": "OSMEN",
      "probability": 0.9965219497680664,
      "signal": "BUY",
      "confidence": 0.9965219497680664,
      "current_price": 8.25,
      "sentiment_score": 0.0,
      "change_1d": -0.12106814291444248,
      "rsi": 20.674692155902733,
      "volatility": 0.10307047430610625,
      "target_price": 8.8275,
      "horizon_days": 10,
      "history_info": "Önceki AL: 8.43 TL (2026-07-13), Mevcut Getiri: %-2.1",
      "reason": "Strong bullish signal (99.7%) > 70.0%",
      "timestamp": "2026-07-14 06:37:20.570487"
    },
    {
      "symbol": "OYAKC",
      "probability": 0.8499846458435059,
      "signal": "BUY",
      "confidence": 0.8499846458435059,
      "current_price": 19.93000030517578,
      "sentiment_score": 0.0,
      "change_1d": -0.20029549100666466,
      "rsi": 33.07020250276224,
      "volatility": 0.07224707065908562,
      "target_price": 21.325100326538088,
      "horizon_days": 10,
      "history_info": "Önceki AL: 20.80 TL (2026-07-02), Mevcut Getiri: %-4.2",
      "reason": "Strong bullish signal (85.0%) > 70.0%",
      "timestamp": "2026-07-14 06:37:23.522251"
    },
    {
      "symbol": "PAPIL",
      "probability": 0.9933369159698486,
      "signal": "BUY",
      "confidence": 0.9933369159698486,
      "current_price": 14.010000228881836,
      "sentiment_score": 0.0,
      "change_1d": -0.1425481430506064,
      "rsi": 19.523437252109005,
      "volatility": 0.08085863646835312,
      "target_price": 14.990700244903564,
      "horizon_days": 10,
      "history_info": "Önceki AL: 14.32 TL (2026-07-10), Mevcut Getiri: %-2.2",
      "reason": "Strong bullish signal (99.3%) > 70.0%",
      "timestamp": "2026-07-14 06:37:24.457281"
    },
    {
      "symbol": "PGSUS",
      "probability": 0.9967278242111206,
      "signal": "BUY",
      "confidence": 0.9967278242111206,
      "current_price": 164.8000030517578,
      "sentiment_score": 0.0,
      "change_1d": -0.12121027166193182,
      "rsi": 31.875493910602657,
      "volatility": 0.1085697603489515,
      "target_price": 176.33600326538087,
      "horizon_days": 10,
      "history_info": "Önceki AL: 170.00 TL (2026-07-13), Mevcut Getiri: %-3.1",
      "reason": "Strong bullish signal (99.7%) > 70.0%",
      "timestamp": "2026-07-14 06:37:27.985131"
    },
    {
      "symbol": "PNLSN",
      "probability": 0.9590321183204651,
      "signal": "BUY",
      "confidence": 0.9590321183204651,
      "current_price": 45.65999984741211,
      "sentiment_score": 0.0,
      "change_1d": -0.3926708215022101,
      "rsi": 25.908366330859806,
      "volatility": 0.28214457992243397,
      "target_price": 48.85619983673096,
      "horizon_days": 10,
      "history_info": "Önceki AL: 44.14 TL (2026-07-10), Mevcut Getiri: %+3.4",
      "reason": "Strong bullish signal (95.9%) > 70.0%",
      "timestamp": "2026-07-14 06:37:28.993296"
    },
    {
      "symbol": "SAFKR",
      "probability": 0.9170908331871033,
      "signal": "BUY",
      "confidence": 0.9170908331871033,
      "current_price": 20.100000381469727,
      "sentiment_score": 0.0,
      "change_1d": 0.19940636386983362,
      "rsi": 27.682206352760787,
      "volatility": 0.15078899231781245,
      "target_price": 21.50700040817261,
      "horizon_days": 10,
      "history_info": "Önceki AL: 19.94 TL (2026-07-07), Mevcut Getiri: %+0.8",
      "reason": "Strong bullish signal (91.7%) > 70.0%",
      "timestamp": "2026-07-14 06:37:38.015357"
    },
    {
      "symbol": "SANFM",
      "probability": 0.9990062117576599,
      "signal": "BUY",
      "confidence": 0.9990062117576599,
      "current_price": 9.979999542236328,
      "sentiment_score": 0.0,
      "change_1d": 0.10029363028793024,
      "rsi": 52.60269533999201,
      "volatility": 0.1665500721430861,
      "target_price": 10.678599510192871,
      "horizon_days": 10,
      "history_info": "Önceki AL: 9.85 TL (2026-07-13), Mevcut Getiri: %+1.3",
      "reason": "Strong bullish signal (99.9%) > 70.0%",
      "timestamp": "2026-07-14 06:37:40.884202"
    },
    {
      "symbol": "SMART",
      "probability": 0.9993969202041626,
      "signal": "BUY",
      "confidence": 0.9993969202041626,
      "current_price": 24.799999237060547,
      "sentiment_score": 0.0,
      "change_1d": -0.24135708695852323,
      "rsi": 32.22082125783338,
      "volatility": 0.07706452416089024,
      "target_price": 26.535999183654788,
      "horizon_days": 10,
      "history_info": "Önceki AL: 25.06 TL (2026-07-13), Mevcut Getiri: %-1.0",
      "reason": "Strong bullish signal (99.9%) > 70.0%",
      "timestamp": "2026-07-14 06:37:50.453347"
    },
    {
      "symbol": "TBORG",
      "probability": 0.9895678162574768,
      "signal": "BUY",
      "confidence": 0.9895678162574768,
      "current_price": 125.80000305175781,
      "sentiment_score": 0.0,
      "change_1d": 0.1592393153395843,
      "rsi": 28.461656603999288,
      "volatility": 0.06433657696192858,
      "target_price": 134.60600326538088,
      "horizon_days": 10,
      "history_info": "Önceki AL: 133.50 TL (2026-07-08), Mevcut Getiri: %-5.8",
      "reason": "Strong bullish signal (99.0%) > 70.0%",
      "timestamp": "2026-07-14 06:38:00.865444"
    },
    {
      "symbol": "TTKOM",
      "probability": 0.9986565113067627,
      "signal": "BUY",
      "confidence": 0.9986565113067627,
      "current_price": 57.70000076293945,
      "sentiment_score": 0.0,
      "change_1d": 0.0,
      "rsi": 54.49320877455624,
      "volatility": 0.05251519353387169,
      "target_price": 61.73900081634522,
      "horizon_days": 10,
      "history_info": "Önceki AL: 57.95 TL (2026-07-13), Mevcut Getiri: %-0.4",
      "reason": "Strong bullish signal (99.9%) > 70.0%",
      "timestamp": "2026-07-14 06:38:08.788808"
    },
    {
      "symbol": "TUKAS",
      "probability": 0.9895855784416199,
      "signal": "BUY",
      "confidence": 0.9895855784416199,
      "current_price": 2.130000114440918,
      "sentiment_score": 0.0,
      "change_1d": 0.0,
      "rsi": 42.496115352983146,
      "volatility": 0.09614468373587173,
      "target_price": 2.279100122451782,
      "horizon_days": 10,
      "history_info": "Önceki AL: 2.13 TL (2026-07-10), Mevcut Getiri: %+0.0",
      "reason": "Strong bullish signal (99.0%) > 70.0%",
      "timestamp": "2026-07-14 06:38:10.626014"
    },
    {
      "symbol": "TUPRS",
      "probability": 0.9998378753662109,
      "signal": "BUY",
      "confidence": 0.9998378753662109,
      "current_price": 268.25,
      "sentiment_score": 0.0,
      "change_1d": -0.3714020427112349,
      "rsi": 51.23953960921339,
      "volatility": 0.10653435089571264,
      "target_price": 287.02750000000003,
      "horizon_days": 10,
      "history_info": "Önceki AL: 263.75 TL (2026-07-10), Mevcut Getiri: %+1.7",
      "reason": "Strong bullish signal (100.0%) > 70.0%",
      "timestamp": "2026-07-14 06:38:11.547635"
    },
    {
      "symbol": "TUREX",
      "probability": 0.997420072555542,
      "signal": "BUY",
      "confidence": 0.997420072555542,
      "current_price": 6.789999961853027,
      "sentiment_score": 0.0,
      "change_1d": 0.1474889636465129,
      "rsi": 29.605052609046467,
      "volatility": 0.10009137586545677,
      "target_price": 7.26529995918274,
      "horizon_days": 10,
      "history_info": "Önceki AL: 6.88 TL (2026-07-10), Mevcut Getiri: %-1.3",
      "reason": "Strong bullish signal (99.7%) > 70.0%",
      "timestamp": "2026-07-14 06:38:12.513294"
    },
    {
      "symbol": "YATAS",
      "probability": 0.9967067837715149,
      "signal": "BUY",
      "confidence": 0.9967067837715149,
      "current_price": 37.18000030517578,
      "sentiment_score": 0.0,
      "change_1d": 0.0,
      "rsi": 24.29011985719295,
      "volatility": 0.08669780042723488,
      "target_price": 39.78260032653809,
      "horizon_days": 10,
      "history_info": "Önceki AL: 38.40 TL (2026-07-10), Mevcut Getiri: %-3.2",
      "reason": "Strong bullish signal (99.7%) > 70.0%",
      "timestamp": "2026-07-14 06:38:21.914828"
    },
    {
      "symbol": "YKBNK",
      "probability": 0.9964145421981812,
      "signal": "BUY",
      "confidence": 0.9964145421981812,
      "current_price": 34.119998931884766,
      "sentiment_score": 0.0,
      "change_1d": -0.11709869937360125,
      "rsi": 30.433082233227438,
      "volatility": 0.12107972616639505,
      "target_price": 36.5083988571167,
      "horizon_days": 10,
      "history_info": "Önceki AL: 35.16 TL (2026-07-13), Mevcut Getiri: %-3.0",
      "reason": "Strong bullish signal (99.6%) > 70.0%",
      "timestamp": "2026-07-14 06:38:23.971673"
    },
    {
      "symbol": "YYLGD",
      "probability": 0.9155446290969849,
      "signal": "BUY",
      "confidence": 0.9155446290969849,
      "current_price": 10.640000343322754,
      "sentiment_score": 0.0,
      "change_1d": -0.37453146732254694,
      "rsi": 35.687036891349024,
      "volatility": 0.0749394184173233,
      "target_price": 11.384800367355348,
      "horizon_days": 10,
      "history_info": "Önceki AL: 10.91 TL (2026-07-03), Mevcut Getiri: %-2.5",
      "reason": "Strong bullish signal (91.6%) > 70.0%",
      "timestamp": "2026-07-14 06:38:24.910035"
    }
  ],
  "sell_signals": [],
  "hold_signals": [],
  "portfolio": {
    "total_equity": 100000.0,
    "daily_pnl": 1250.0,
    "daily_pnl_pct": 1.25,
    "holdings": []
  },
  "config": {
    "entry_threshold": 0.7,
    "stop_loss": 0.03
  }
}